{
  "grid_id": "0aa2f5ac-05ee-43f2-874f-b246c0f3c868",
  "hexes": {
    "0,0": {
      "coordinates": [
        0,
        0
      ],
      "name": "Initial Landing Site",
      "generated": true,
      "biome": "Plains",
      "description": "A vast expanse of plains.",
      "traversable_sides": {
        "N": true,
        "S": true,
        "NE": true,
        "NW": true,
        "SE": true,
        "SW": true
      },
      "interest_points": [],
      "resourceNodes": [],
      "openedContainers": {},
      "visited": true,
      "inLineOfSight": false,
      "namingSource": "engine",
      "visualVariant": 1,
      "npcs": [
        "4aaaf698-0a94-449b-9972-04d53f643d5e"
      ]
    },
    "0,1": {
      "coordinates": [
        0,
        1
      ],
      "name": "Plains (Uncharted Territory)",
      "generated": true,
      "biome": "Plains",
      "description": "A vast expanse of plains.",
      "traversable_sides": {
        "N": true,
        "S": true,
        "NE": true,
        "NW": true,
        "SE": true,
        "SW": true
      },
      "interest_points": [],
      "resourceNodes": [],
      "openedContainers": {},
      "visited": false,
      "inLineOfSight": true,
      "namingSource": "engine",
      "visualVariant": 4,
      "npcs": [
        "24c4ff66-e559-4806-b8f2-0e138164adaf"
      ],
      "connections": "0:R:1,1:R:1,5:R:1"
    },
    "0,-1": {
      "coordinates": [
        0,
        -1
      ],
      "name": "Hills (Uncharted Territory)",
      "generated": true,
      "biome": "Hills",
      "description": "A vast expanse of hills.",
      "traversable_sides": {
        "N": true,
        "S": true,
        "NE": true,
        "NW": true,
        "SE": true,
        "SW": true
      },
      "interest_points": [],
      "resourceNodes": [],
      "openedContainers": {},
      "visited": false,
      "inLineOfSight": true,
      "namingSource": "engine",
      "visualVariant": 5,
      "npcs": []
    },
    "1,0": {
      "coordinates": [
        1,
        0
      ],
      "name": "Jungle (Uncharted Territory)",
      "generated": true,
      "biome": "Jungle",
      "description": "A vast expanse of jungle.",
      "traversable_sides": {
        "N": true,
        "S": true,
        "NE": true,
        "NW": true,
        "SE": true,
        "SW": true
      },
      "interest_points": [],
      "resourceNodes": [
        {
          "id": "node_w25ce6qix",
          "resourceType": "Herb",
          "itemId": "Silverleaf",
          "quantityRemaining": 1,
          "respawnDays": 7,
          "skillCheck": {
            "skill": "Nature",
            "dc": 10
          }
        }
      ],
      "openedContainers": {},
      "visited": false,
      "inLineOfSight": true,
      "namingSource": "engine",
      "visualVariant": 5,
      "npcs": [],
      "connections": "1:P:1,2:P:0"
    },
    "-1,1": {
      "coordinates": [
        -1,
        1
      ],
      "name": "Plains (Uncharted Territory)",
      "generated": true,
      "biome": "Plains",
      "description": "A vast expanse of plains.",
      "traversable_sides": {
        "N": true,
        "S": true,
        "NE": true,
        "NW": true,
        "SE": true,
        "SW": true
      },
      "interest_points": [],
      "resourceNodes": [],
      "openedContainers": {},
      "visited": false,
      "inLineOfSight": true,
      "namingSource": "engine",
      "visualVariant": 3,
      "npcs": [
        "25683e34-c0fe-424d-9c05-554caee6f739"
      ],
      "connections": "0:R:1,5:R:1,4:R:1"
    },
    "1,-1": {
      "coordinates": [
        1,
        -1
      ],
      "name": "Hills (Uncharted Territory)",
      "generated": true,
      "biome": "Hills",
      "description": "A vast expanse of hills.",
      "traversable_sides": {
        "N": true,
        "S": true,
        "NE": true,
        "NW": true,
        "SE": true,
        "SW": true
      },
      "interest_points": [],
      "resourceNodes": [],
      "openedContainers": {},
      "visited": false,
      "inLineOfSight": true,
      "namingSource": "engine",
      "visualVariant": 4,
      "npcs": []
    },
    "-1,0": {
      "coordinates": [
        -1,
        0
      ],
      "name": "Plains (Uncharted Territory)",
      "generated": true,
      "biome": "Plains",
      "description": "A vast expanse of plains.",
      "traversable_sides": {
        "N": true,
        "S": true,
        "NE": true,
        "NW": true,
        "SE": true,
        "SW": true
      },
      "interest_points": [],
      "resourceNodes": [],
      "openedContainers": {},
      "visited": false,
      "inLineOfSight": true,
      "namingSource": "engine",
      "visualVariant": 2,
      "npcs": [],
      "connections": "3:R:1,5:R:1,4:R:1"
    },
    "0,2": {
      "coordinates": [
        0,
        2
      ],
      "generated": true,
      "visited": false,
      "biome": "Jungle",
      "name": "Uncharted Territory",
      "description": "The mists of the unknown cling to this place.",
      "inLineOfSight": false,
      "interest_points": [],
      "resourceNodes": [
        {
          "id": "node_o8l0g3z7v",
          "resourceType": "Herb",
          "itemId": "Silverleaf",
          "quantityRemaining": 1,
          "respawnDays": 7,
          "skillCheck": {
            "skill": "Nature",
            "dc": 10
          }
        }
      ],
      "openedContainers": {},
      "namingSource": "engine",
      "visualVariant": 5,
      "npcs": [
        "94b5e5f9-39ca-4ff2-af7d-70f055343bc3"
      ],
      "isQuestReserved": false,
      "isNpcNamed": false,
      "fogOfWarLevel": "HIDDEN",
      "traversable_sides": {
        "N": true,
        "S": true,
        "NE": true,
        "NW": true,
        "SE": true,
        "SW": true
      },
      "connections": "3:P:1,4:P:0"
    },
    "1,1": {
      "coordinates": [
        1,
        1
      ],
      "generated": true,
      "visited": false,
      "biome": "Jungle",
      "name": "Uncharted Territory",
      "description": "The mists of the unknown cling to this place.",
      "inLineOfSight": false,
      "interest_points": [],
      "resourceNodes": [
        {
          "id": "node_5bk0xar2s",
          "resourceType": "Wood",
          "itemId": "Ironwood",
          "quantityRemaining": 1,
          "respawnDays": 7,
          "skillCheck": {
            "skill": "Nature",
            "dc": 10
          }
        }
      ],
      "openedContainers": {},
      "namingSource": "engine",
      "visualVariant": 4,
      "npcs": [],
      "isQuestReserved": false,
      "isNpcNamed": false,
      "fogOfWarLevel": "HIDDEN",
      "traversable_sides": {
        "N": true,
        "S": true,
        "NE": true,
        "NW": true,
        "SE": true,
        "SW": true
      },
      "connections": "4:P:1,2:P:1"
    },
    "-1,2": {
      "coordinates": [
        -1,
        2
      ],
      "generated": true,
      "visited": false,
      "biome": "Jungle",
      "name": "Uncharted Territory",
      "description": "The mists of the unknown cling to this place.",
      "inLineOfSight": false,
      "interest_points": [],
      "resourceNodes": [
        {
          "id": "node_js42hxz9m",
          "resourceType": "Ore",
          "itemId": "Iron_Ore",
          "quantityRemaining": 3,
          "respawnDays": 7,
          "skillCheck": {
            "skill": "Nature",
            "dc": 10
          }
        }
      ],
      "openedContainers": {},
      "namingSource": "engine",
      "visualVariant": 3,
      "npcs": [
        "9b7bad6a-38ec-4e78-95c6-3dc323019d04"
      ],
      "isQuestReserved": false,
      "isNpcNamed": false,
      "fogOfWarLevel": "HIDDEN",
      "traversable_sides": {
        "N": true,
        "S": true,
        "NE": true,
        "NW": true,
        "SE": true,
        "SW": true
      },
      "connections": "3:P:1,1:P:0,2:P:1"
    },
    "0,-2": {
      "coordinates": [
        0,
        -2
      ],
      "generated": true,
      "visited": false,
      "biome": "Mountains",
      "name": "Uncharted Territory",
      "description": "The mists of the unknown cling to this place.",
      "inLineOfSight": false,
      "interest_points": [],
      "resourceNodes": [],
      "openedContainers": {},
      "namingSource": "engine",
      "visualVariant": 5,
      "npcs": [],
      "isQuestReserved": false,
      "isNpcNamed": false,
      "fogOfWarLevel": "HIDDEN",
      "traversable_sides": {
        "N": true,
        "S": true,
        "NE": true,
        "NW": true,
        "SE": true,
        "SW": true
      }
    },
    "1,-2": {
      "coordinates": [
        1,
        -2
      ],
      "generated": true,
      "visited": false,
      "biome": "Mountains",
      "name": "Uncharted Territory",
      "description": "The mists of the unknown cling to this place.",
      "inLineOfSight": false,
      "interest_points": [],
      "resourceNodes": [
        {
          "id": "node_7t6qituen",
          "resourceType": "Ore",
          "itemId": "Iron_Ore",
          "quantityRemaining": 1,
          "respawnDays": 7,
          "skillCheck": {
            "skill": "Nature",
            "dc": 10
          }
        }
      ],
      "openedContainers": {},
      "namingSource": "engine",
      "visualVariant": 3,
      "npcs": [],
      "isQuestReserved": false,
      "isNpcNamed": false,
      "fogOfWarLevel": "HIDDEN",
      "traversable_sides": {
        "N": true,
        "S": true,
        "NE": true,
        "NW": true,
        "SE": true,
        "SW": true
      }
    },
    "-1,-1": {
      "coordinates": [
        -1,
        -1
      ],
      "generated": true,
      "visited": false,
      "biome": "Hills",
      "name": "Uncharted Territory",
      "description": "The mists of the unknown cling to this place.",
      "inLineOfSight": false,
      "interest_points": [],
      "resourceNodes": [],
      "openedContainers": {},
      "namingSource": "engine",
      "visualVariant": 4,
      "npcs": [],
      "isQuestReserved": false,
      "isNpcNamed": false,
      "fogOfWarLevel": "HIDDEN",
      "traversable_sides": {
        "N": true,
        "S": true,
        "NE": true,
        "NW": true,
        "SE": true,
        "SW": true
      },
      "connections": "0:P:1,5:P:1"
    },
    "2,0": {
      "coordinates": [
        2,
        0
      ],
      "generated": true,
      "visited": false,
      "biome": "Plains",
      "name": "Uncharted Territory",
      "description": "The mists of the unknown cling to this place.",
      "inLineOfSight": false,
      "interest_points": [],
      "resourceNodes": [
        {
          "id": "node_yp0u06bky",
          "resourceType": "Hide",
          "itemId": "Raw_Hide",
          "quantityRemaining": 2,
          "respawnDays": 7,
          "skillCheck": {
            "skill": "Nature",
            "dc": 10
          }
        }
      ],
      "openedContainers": {},
      "namingSource": "engine",
      "visualVariant": 4,
      "npcs": [],
      "isQuestReserved": false,
      "isNpcNamed": false,
      "fogOfWarLevel": "HIDDEN",
      "traversable_sides": {
        "N": true,
        "S": true,
        "NE": true,
        "NW": true,
        "SE": true,
        "SW": true
      },
      "connections": "5:R:1,4:R:1,3:R:1"
    },
    "2,-1": {
      "coordinates": [
        2,
        -1
      ],
      "generated": true,
      "visited": false,
      "biome": "Hills",
      "name": "Uncharted Territory",
      "description": "The mists of the unknown cling to this place.",
      "inLineOfSight": false,
      "interest_points": [],
      "resourceNodes": [],
      "openedContainers": {},
      "namingSource": "engine",
      "visualVariant": 5,
      "npcs": [],
      "isQuestReserved": false,
      "isNpcNamed": false,
      "fogOfWarLevel": "HIDDEN",
      "traversable_sides": {
        "N": true,
        "S": true,
        "NE": true,
        "NW": true,
        "SE": true,
        "SW": true
      },
      "connections": "0:P:1,5:P:0"
    },
    "-2,2": {
      "coordinates": [
        -2,
        2
      ],
      "generated": true,
      "visited": false,
      "biome": "Jungle",
      "name": "Uncharted Territory",
      "description": "The mists of the unknown cling to this place.",
      "inLineOfSight": false,
      "interest_points": [],
      "resourceNodes": [],
      "openedContainers": {},
      "namingSource": "engine",
      "visualVariant": 2,
      "npcs": [],
      "isQuestReserved": false,
      "isNpcNamed": false,
      "fogOfWarLevel": "HIDDEN",
      "traversable_sides": {
        "N": true,
        "S": true,
        "NE": true,
        "NW": true,
        "SE": true,
        "SW": true
      },
      "connections": "2:P:1"
    },
    "-2,1": {
      "coordinates": [
        -2,
        1
      ],
      "generated": true,
      "visited": false,
      "biome": "Jungle",
      "name": "Uncharted Territory",
      "description": "The mists of the unknown cling to this place.",
      "inLineOfSight": false,
      "interest_points": [],
      "resourceNodes": [
        {
          "id": "node_fcc2ysocy",
          "resourceType": "Herb",
          "itemId": "Kingsbloom",
          "quantityRemaining": 3,
          "respawnDays": 7,
          "skillCheck": {
            "skill": "Nature",
            "dc": 10
          }
        }
      ],
      "openedContainers": {},
      "namingSource": "engine",
      "visualVariant": 1,
      "npcs": [],
      "isQuestReserved": false,
      "isNpcNamed": false,
      "fogOfWarLevel": "HIDDEN",
      "traversable_sides": {
        "N": true,
        "S": true,
        "NE": true,
        "NW": true,
        "SE": true,
        "SW": true
      },
      "connections": "1:P:1,2:P:1,3:P:1"
    },
    "2,-2": {
      "coordinates": [
        2,
        -2
      ],
      "generated": true,
      "visited": false,
      "biome": "Mountains",
      "name": "Uncharted Territory",
      "description": "The mists of the unknown cling to this place.",
      "inLineOfSight": false,
      "interest_points": [],
      "resourceNodes": [
        {
          "id": "node_gw5giitg4",
          "resourceType": "Ore",
          "itemId": "Iron_Ore",
          "quantityRemaining": 2,
          "respawnDays": 7,
          "skillCheck": {
            "skill": "Nature",
            "dc": 10
          }
        }
      ],
      "openedContainers": {},
      "namingSource": "engine",
      "visualVariant": 4,
      "npcs": [],
      "isQuestReserved": false,
      "isNpcNamed": false,
      "fogOfWarLevel": "HIDDEN",
      "traversable_sides": {
        "N": true,
        "S": true,
        "NE": true,
        "NW": true,
        "SE": true,
        "SW": true
      }
    },
    "-2,0": {
      "coordinates": [
        -2,
        0
      ],
      "generated": true,
      "visited": false,
      "biome": "Plains",
      "name": "Uncharted Territory",
      "description": "The mists of the unknown cling to this place.",
      "inLineOfSight": false,
      "interest_points": [],
      "resourceNodes": [
        {
          "id": "node_5lfqkgivl",
          "resourceType": "Hide",
          "itemId": "Raw_Hide",
          "quantityRemaining": 2,
          "respawnDays": 7,
          "skillCheck": {
            "skill": "Nature",
            "dc": 10
          }
        }
      ],
      "openedContainers": {},
      "namingSource": "engine",
      "visualVariant": 3,
      "npcs": [],
      "isQuestReserved": false,
      "isNpcNamed": false,
      "fogOfWarLevel": "HIDDEN",
      "traversable_sides": {
        "N": true,
        "S": true,
        "NE": true,
        "NW": true,
        "SE": true,
        "SW": true
      },
      "connections": "0:R:1,1:R:1,2:R:1"
    }
  },
  "discoveredHexIds": [
    "0,0"
  ],
  "lastGeneratedTurn": 0,
  "coastlines": []
}