{
  "grid_id": "world_map",
  "hexes": {
    "0,0": {
      "coordinates": [
        0,
        0
      ],
      "name": "Initial Landing Site",
      "generated": true,
      "biome": "Plains",
      "description": "A vast expanse of hills.",
      "traversable_sides": {
        "N": true,
        "S": true,
        "NE": true,
        "NW": true,
        "SE": true,
        "SW": true
      },
      "interest_points": [],
      "resourceNodes": [],
      "openedContainers": {},
      "visited": true,
      "inLineOfSight": false,
      "namingSource": "engine",
      "visualVariant": 1
    },
    "0,1": {
      "coordinates": [
        0,
        1
      ],
      "name": "Plains (Uncharted Territory)",
      "generated": true,
      "biome": "Plains",
      "description": "A vast expanse of plains.",
      "traversable_sides": {
        "N": true,
        "S": true,
        "NE": true,
        "NW": true,
        "SE": true,
        "SW": true
      },
      "interest_points": [],
      "resourceNodes": [
        {
          "id": "node_42w8j57rs",
          "resourceType": "Herb",
          "itemId": "Kingsbloom",
          "quantityRemaining": 3,
          "respawnDays": 7,
          "skillCheck": {
            "skill": "Nature",
            "dc": 10
          }
        }
      ],
      "openedContainers": {},
      "visited": false,
      "inLineOfSight": true,
      "namingSource": "engine",
      "visualVariant": 4
    },
    "0,-1": {
      "coordinates": [
        0,
        -1
      ],
      "name": "Tundra (Uncharted Territory)",
      "generated": true,
      "biome": "Tundra",
      "description": "A vast expanse of tundra.",
      "traversable_sides": {
        "N": true,
        "S": true,
        "NE": true,
        "NW": true,
        "SE": true,
        "SW": true
      },
      "interest_points": [],
      "resourceNodes": [
        {
          "id": "node_0e1bjagv4",
          "resourceType": "Hide",
          "itemId": "Thick_Hide",
          "quantityRemaining": 3,
          "respawnDays": 7,
          "skillCheck": {
            "skill": "Nature",
            "dc": 10
          }
        }
      ],
      "openedContainers": {},
      "visited": false,
      "inLineOfSight": true,
      "namingSource": "engine",
      "visualVariant": 5
    },
    "1,0": {
      "coordinates": [
        1,
        0
      ],
      "name": "Farmland (Uncharted Territory)",
      "generated": true,
      "biome": "Farmland",
      "description": "A vast expanse of farmland.",
      "traversable_sides": {
        "N": true,
        "S": true,
        "NE": true,
        "NW": true,
        "SE": true,
        "SW": true
      },
      "interest_points": [],
      "resourceNodes": [],
      "openedContainers": {},
      "visited": false,
      "inLineOfSight": true,
      "namingSource": "engine",
      "visualVariant": 5
    },
    "-1,1": {
      "coordinates": [
        -1,
        1
      ],
      "name": "Ruins (Uncharted Territory)",
      "generated": true,
      "biome": "Ruins",
      "description": "A vast expanse of ruins.",
      "traversable_sides": {
        "N": true,
        "S": true,
        "NE": true,
        "NW": true,
        "SE": true,
        "SW": true
      },
      "interest_points": [],
      "resourceNodes": [],
      "openedContainers": {},
      "visited": false,
      "inLineOfSight": true,
      "namingSource": "engine",
      "visualVariant": 14
    },
    "1,-1": {
      "coordinates": [
        1,
        -1
      ],
      "name": "Hills (Uncharted Territory)",
      "generated": true,
      "biome": "Hills",
      "description": "A vast expanse of hills.",
      "traversable_sides": {
        "N": true,
        "S": true,
        "NE": true,
        "NW": true,
        "SE": true,
        "SW": true
      },
      "interest_points": [],
      "resourceNodes": [],
      "openedContainers": {},
      "visited": false,
      "inLineOfSight": true,
      "namingSource": "engine",
      "visualVariant": 5
    },
    "-1,0": {
      "coordinates": [
        -1,
        0
      ],
      "name": "Plains (Uncharted Territory)",
      "generated": true,
      "biome": "Plains",
      "description": "A vast expanse of plains.",
      "traversable_sides": {
        "N": true,
        "S": true,
        "NE": true,
        "NW": true,
        "SE": true,
        "SW": true
      },
      "interest_points": [],
      "resourceNodes": [],
      "openedContainers": {},
      "visited": false,
      "inLineOfSight": true,
      "namingSource": "engine",
      "visualVariant": 3
    },
    "0,2": {
      "coordinates": [
        0,
        2
      ],
      "generated": true,
      "visited": false,
      "biome": "Plains",
      "name": "Uncharted Territory",
      "description": "A vast expanse of plains.",
      "inLineOfSight": false,
      "interest_points": [],
      "resourceNodes": [
        {
          "id": "node_tv1eogkb8",
          "resourceType": "Hide",
          "itemId": "Raw_Hide",
          "quantityRemaining": 2,
          "respawnDays": 7,
          "skillCheck": {
            "skill": "Nature",
            "dc": 10
          }
        }
      ],
      "openedContainers": {},
      "namingSource": "engine",
      "visualVariant": 3,
      "traversable_sides": {
        "N": true,
        "S": true,
        "NE": true,
        "NW": true,
        "SE": true,
        "SW": true
      }
    },
    "1,1": {
      "coordinates": [
        1,
        1
      ],
      "generated": true,
      "visited": false,
      "biome": "Forest",
      "name": "Uncharted Territory",
      "description": "A vast expanse of forest.",
      "inLineOfSight": false,
      "interest_points": [],
      "resourceNodes": [
        {
          "id": "node_hiy1wri6j",
          "resourceType": "Herb",
          "itemId": "Silverleaf",
          "quantityRemaining": 1,
          "respawnDays": 7,
          "skillCheck": {
            "skill": "Nature",
            "dc": 10
          }
        }
      ],
      "openedContainers": {},
      "namingSource": "engine",
      "visualVariant": 7,
      "traversable_sides": {
        "N": true,
        "S": true,
        "NE": true,
        "NW": true,
        "SE": true,
        "SW": true
      }
    },
    "-1,2": {
      "coordinates": [
        -1,
        2
      ],
      "generated": true,
      "visited": false,
      "biome": "Jungle",
      "name": "Uncharted Territory",
      "description": "A vast expanse of jungle.",
      "inLineOfSight": false,
      "interest_points": [],
      "resourceNodes": [
        {
          "id": "node_p8qcrgx1w",
          "resourceType": "Wood",
          "itemId": "Ironwood",
          "quantityRemaining": 3,
          "respawnDays": 7,
          "skillCheck": {
            "skill": "Nature",
            "dc": 10
          }
        }
      ],
      "openedContainers": {},
      "namingSource": "engine",
      "visualVariant": 3,
      "traversable_sides": {
        "N": true,
        "S": true,
        "NE": true,
        "NW": true,
        "SE": true,
        "SW": true
      }
    },
    "0,-2": {
      "coordinates": [
        0,
        -2
      ],
      "generated": true,
      "visited": false,
      "biome": "Hills",
      "name": "Uncharted Territory",
      "description": "A vast expanse of hills.",
      "inLineOfSight": false,
      "interest_points": [],
      "resourceNodes": [],
      "openedContainers": {},
      "namingSource": "engine",
      "visualVariant": 5,
      "traversable_sides": {
        "N": true,
        "S": true,
        "NE": true,
        "NW": true,
        "SE": true,
        "SW": true
      }
    },
    "1,-2": {
      "coordinates": [
        1,
        -2
      ],
      "generated": true,
      "visited": false,
      "biome": "Desert",
      "name": "Uncharted Territory",
      "description": "A vast expanse of desert.",
      "inLineOfSight": false,
      "interest_points": [],
      "resourceNodes": [],
      "openedContainers": {},
      "namingSource": "engine",
      "visualVariant": 3,
      "traversable_sides": {
        "N": true,
        "S": true,
        "NE": true,
        "NW": true,
        "SE": true,
        "SW": true
      }
    },
    "-1,-1": {
      "coordinates": [
        -1,
        -1
      ],
      "generated": true,
      "visited": false,
      "biome": "Jungle",
      "name": "Uncharted Territory",
      "description": "A vast expanse of jungle.",
      "inLineOfSight": false,
      "interest_points": [],
      "resourceNodes": [],
      "openedContainers": {},
      "namingSource": "engine",
      "visualVariant": 5,
      "traversable_sides": {
        "N": true,
        "S": true,
        "NE": true,
        "NW": true,
        "SE": true,
        "SW": true
      }
    },
    "2,0": {
      "coordinates": [
        2,
        0
      ],
      "generated": true,
      "visited": false,
      "biome": "Farmland",
      "name": "Uncharted Territory",
      "description": "A vast expanse of farmland.",
      "inLineOfSight": false,
      "interest_points": [],
      "resourceNodes": [],
      "openedContainers": {},
      "namingSource": "engine",
      "visualVariant": 4,
      "traversable_sides": {
        "N": true,
        "S": true,
        "NE": true,
        "NW": true,
        "SE": true,
        "SW": true
      }
    },
    "2,-1": {
      "coordinates": [
        2,
        -1
      ],
      "generated": true,
      "visited": false,
      "biome": "Farmland",
      "name": "Uncharted Territory",
      "description": "A vast expanse of farmland.",
      "inLineOfSight": false,
      "interest_points": [],
      "resourceNodes": [
        {
          "id": "node_m5ky8dkkr",
          "resourceType": "Arcane",
          "itemId": "Hay",
          "quantityRemaining": 1,
          "respawnDays": 7,
          "skillCheck": {
            "skill": "Nature",
            "dc": 10
          }
        }
      ],
      "openedContainers": {},
      "namingSource": "engine",
      "visualVariant": 3,
      "traversable_sides": {
        "N": true,
        "S": true,
        "NE": true,
        "NW": true,
        "SE": true,
        "SW": true
      }
    },
    "-2,2": {
      "coordinates": [
        -2,
        2
      ],
      "generated": true,
      "visited": false,
      "biome": "Plains",
      "name": "Uncharted Territory",
      "description": "A vast expanse of plains.",
      "inLineOfSight": false,
      "interest_points": [],
      "resourceNodes": [],
      "openedContainers": {},
      "namingSource": "engine",
      "visualVariant": 4,
      "traversable_sides": {
        "N": true,
        "S": true,
        "NE": true,
        "NW": true,
        "SE": true,
        "SW": true
      }
    },
    "-2,1": {
      "coordinates": [
        -2,
        1
      ],
      "generated": true,
      "visited": false,
      "biome": "Ruins",
      "name": "Uncharted Territory",
      "description": "A vast expanse of ruins.",
      "inLineOfSight": false,
      "interest_points": [],
      "resourceNodes": [
        {
          "id": "node_qxemwpohl",
          "resourceType": "Ore",
          "itemId": "Silver_Ore",
          "quantityRemaining": 3,
          "respawnDays": 7,
          "skillCheck": {
            "skill": "Nature",
            "dc": 10
          }
        }
      ],
      "openedContainers": {},
      "namingSource": "engine",
      "visualVariant": 20,
      "traversable_sides": {
        "N": true,
        "S": true,
        "NE": true,
        "NW": true,
        "SE": true,
        "SW": true
      }
    },
    "2,-2": {
      "coordinates": [
        2,
        -2
      ],
      "generated": true,
      "visited": false,
      "biome": "Plains",
      "name": "Uncharted Territory",
      "description": "A vast expanse of plains.",
      "inLineOfSight": false,
      "interest_points": [],
      "resourceNodes": [
        {
          "id": "node_prq1nn2y0",
          "resourceType": "Herb",
          "itemId": "Kingsbloom",
          "quantityRemaining": 1,
          "respawnDays": 7,
          "skillCheck": {
            "skill": "Nature",
            "dc": 10
          }
        }
      ],
      "openedContainers": {},
      "namingSource": "engine",
      "visualVariant": 2,
      "traversable_sides": {
        "N": true,
        "S": true,
        "NE": true,
        "NW": true,
        "SE": true,
        "SW": true
      }
    },
    "-2,0": {
      "coordinates": [
        -2,
        0
      ],
      "generated": true,
      "visited": false,
      "biome": "Jungle",
      "name": "Uncharted Territory",
      "description": "A vast expanse of jungle.",
      "inLineOfSight": false,
      "interest_points": [],
      "resourceNodes": [],
      "openedContainers": {},
      "namingSource": "engine",
      "visualVariant": 4,
      "traversable_sides": {
        "N": true,
        "S": true,
        "NE": true,
        "NW": true,
        "SE": true,
        "SW": true
      }
    }
  },
  "discoveredHexIds": [
    "0,0"
  ],
  "lastGeneratedTurn": 0,
  "coastlines": []
}